bridgezero/__init__.py
bridgezero/bridge.py
bridgezero-0.1.3.dist-info/LICENSE.txt
bridgezero-0.1.3.dist-info/METADATA
bridgezero-0.1.3.dist-info/WHEEL
bridgezero-0.1.3.dist-info/top_level.txt
bridgezero-0.1.3.dist-info/RECORD
