Metadata-Version: 2.1
Name: bridgezero
Version: 0.1.3
Summary: BridgeZero.ai Reinforcement Learning Bridge Bidding
Author: Wojciech Peisert
Author-email: wojtekp@sauron.pl
License: LICENCE.txt
License-File: LICENSE.txt
Requires-Dist: numpy
Requires-Dist: bridgelib
